MANIFEST.in
README.rst
requirements.txt
setup.py
docs/index.rst
docs/ref/profile.rst
scripts/shaker
scripts/shaker-terminate
shaker/__init__.py
shaker/ami.py
shaker/config.py
shaker/log.py
shaker/template.py
shaker/version.py
shaker.egg-info/PKG-INFO
shaker.egg-info/SOURCES.txt
shaker.egg-info/dependency_links.txt
shaker.egg-info/requires.txt
shaker.egg-info/top_level.txt