Metadata-Version: 1.1
Name: shaker
Version: 0.1.3
Summary: EC2 Salt Minion Launcher
Home-page: https://github.com/rubic/shaker
Author: Jeff Bauer
Author-email: jbauer@rubic.com
License: UNKNOWN
Keywords: salt,ec2,aws
Platform: UNKNOWN
Classifier: Programming Language :: Python
Classifier: Programming Language :: Python :: 2.6
Classifier: Programming Language :: Python :: 2.7
Classifier: Development Status :: 3 - Alpha
Classifier: Environment :: Console
Classifier: Intended Audience :: Developers
Classifier: License :: OSI Approved :: BSD License
Classifier: Operating System :: POSIX
Classifier: Topic :: System :: Distributed Computing
Classifier: Topic :: System :: Systems Administration
